ckanext_sso-1.0.5-py3.13-nspkg.pth
ckanext/sso/__init__.py
ckanext/sso/helpers.py
ckanext/sso/ldap_client.py
ckanext/sso/plugin.py
ckanext/sso/ssoclient.py
ckanext/sso/views.py
ckanext/sso/assets/webassets.yml
ckanext/sso/i18n/de/LC_MESSAGES/ckanext-sso.mo
ckanext/sso/templates/user/snippets/login_form.html
ckanext/sso/templates/user/snippets/new.html
ckanext_sso-1.0.5.dist-info/licenses/LICENSE
ckanext_sso-1.0.5.dist-info/METADATA
ckanext_sso-1.0.5.dist-info/WHEEL
ckanext_sso-1.0.5.dist-info/entry_points.txt
ckanext_sso-1.0.5.dist-info/namespace_packages.txt
ckanext_sso-1.0.5.dist-info/top_level.txt
ckanext_sso-1.0.5.dist-info/RECORD
