Metadata-Version: 2.4
Name: ckanext-sso
Version: 1.0.5
Summary: An extension for authentication with OIDC/Keycloak
Home-page: https://github.com/Mat-O-Lab/ckanext-sso
Author: Thomas Hanke
Author-email: thomas.hanke@iwm.fraunhofer.de
License: AGPL
Keywords: CKAN SSO OIDC
Classifier: Development Status :: 4 - Beta
Classifier: License :: OSI Approved :: GNU Affero General Public License v3 or later (AGPLv3+)
Classifier: Programming Language :: Python :: 3.11
License-File: LICENSE
Requires-Dist: requests-oauthlib==1.3.1
Requires-Dist: PyJWT==1.7.1
Requires-Dist: ldap3
Dynamic: author
Dynamic: author-email
Dynamic: classifier
Dynamic: description
Dynamic: description-content-type
Dynamic: home-page
Dynamic: keywords
Dynamic: license
Dynamic: license-file
Dynamic: requires-dist
Dynamic: summary
